cv_aid/__init__.py
cv_aid/_dlib.py
cv_aid/_mediapipe.py
cv_aid/frame.py
cv_aid/haarcascades.py
cv_aid/stream.py
cv_aid/utils.py
scripts.py
tests/egypt.webp
tests/test.webp
tests/test_concatenated.webp
tests/test_frame.py
tests/test_line.webp
tests/test_misc.py
tests/test_rotate.webp
tests/test_rotated.webp
tests/test_stacked.webp
tests/test_utils.py
cv_aid-1.0.1.dist-info/entry_points.txt
cv_aid-1.0.1.dist-info/LICENSE
cv_aid-1.0.1.dist-info/WHEEL
cv_aid-1.0.1.dist-info/METADATA
cv_aid-1.0.1.dist-info/RECORD
