Metadata-Version: 2.1
Name: cv-aid
Version: 1.0.1
Summary: CV Aid is a set of helpers for computer vision tasks.
Home-page: https://khalidelboray.me/cv-aid
License: GNU Version 3
Keywords: computer vision,cv,image,processing,helpers,open-cv,dlib,face detection
Author: Khalid Mohamed Elborai
Author-email: accnew820@gmail.com
Requires-Python: >=3.8,<4.0
Classifier: License :: Other/Proprietary License
Classifier: Programming Language :: Python :: 3
Classifier: Programming Language :: Python :: 3.10
Classifier: Programming Language :: Python :: 3.8
Classifier: Programming Language :: Python :: 3.9
Requires-Dist: cmake (>=3.22.1,<4.0.0)
Requires-Dist: deepstack-sdk (>=0.2.1,<0.3.0)
Requires-Dist: dlib (>=19.22.1,<20.0.0)
Requires-Dist: filetype (>=1.0.9,<2.0.0)
Requires-Dist: numpy (>=1.21,<2.0)
Requires-Dist: opencv-python (>=4.1.0,<5.0.0)
Requires-Dist: requests (>=2.27.1,<3.0.0)
Requires-Dist: tqdm (>=4.62.3,<5.0.0)
Project-URL: Repository, https://github.com/khalidelboray/cv-aid
